report_racing/__init__.py
report_racing/report_racing.py
report_racing-1.4.dist-info/METADATA
report_racing-1.4.dist-info/WHEEL
report_racing-1.4.dist-info/top_level.txt
report_racing-1.4.dist-info/RECORD
