Metadata-Version: 2.1
Name: report-racing
Version: 1.4
Summary: UNKNOWN
Home-page: UNKNOWN
Author-email: dimapyatetsky@gmail.com
License: UNKNOWN
Platform: UNKNOWN
